ipay_sdk/__init__.py
ipay_sdk/config.py
ipay_sdk/gateway.py
ipay_sdk/helpers.py
ipay_sdk/schemas.py
tests/__init__.py
tests/base.py
tests/test_card_payment.py
tests/test_generate_checkout_page.py
tests/test_payment_status.py
ipay_sdk-0.0.4.dist-info/LICENSE
ipay_sdk-0.0.4.dist-info/METADATA
ipay_sdk-0.0.4.dist-info/WHEEL
ipay_sdk-0.0.4.dist-info/top_level.txt
ipay_sdk-0.0.4.dist-info/RECORD
